lpfgopt/VERSION.txt
lpfgopt/__init__.py
lpfgopt/leapfrog.py
lpfgopt/scipy_min.py
lpfgopt_lite-0.9.2.dist-info/LICENCE.txt
lpfgopt_lite-0.9.2.dist-info/METADATA
lpfgopt_lite-0.9.2.dist-info/WHEEL
lpfgopt_lite-0.9.2.dist-info/top_level.txt
lpfgopt_lite-0.9.2.dist-info/RECORD
