Metadata-Version: 2.1
Name: lpfgopt-lite
Version: 0.9.2
Summary: Leap Frog Optimizer - Lite Edition
Home-page: http://www.r3eda.com/
Author: Mark E. Redd
Author-email: redddogjr@gmail.com
License: MIT
Download-URL: https://github.com/flythereddflagg/lpfgopt
Keywords: optimization direct-search gradient-free
Platform: UNKNOWN
Classifier: Development Status :: 4 - Beta
Classifier: Intended Audience :: Science/Research
Classifier: Intended Audience :: Manufacturing
Classifier: Intended Audience :: Education
Classifier: Intended Audience :: End Users/Desktop
Classifier: License :: OSI Approved :: MIT License
Requires-Python: >=3.6
Requires-Dist: nose
Requires-Dist: numpy
Requires-Dist: scipy
